<annotation>
	<folder>train</folder>
	<filename>2-500x500.jpeg</filename>
	<path>H:\python_practice\feed_bag_project\feed\Tensorflow\workspace\images\train\2-500x500.jpeg</path>
	<source>
		<database>Unknown</database>
	</source>
	<size>
		<width>375</width>
		<height>500</height>
		<depth>3</depth>
	</size>
	<segmented>0</segmented>
	<object>
		<name>feed_bag</name>
		<pose>Unspecified</pose>
		<truncated>1</truncated>
		<difficult>0</difficult>
		<bndbox>
			<xmin>2</xmin>
			<ymin>7</ymin>
			<xmax>375</xmax>
			<ymax>500</ymax>
		</bndbox>
	</object>
</annotation>
